markdup/__init__.py
markdup/cli.py
markdup/deduplication.py
markdup/utils.py
markdup-0.0.25.dist-info/licenses/LICENSE
markdup-0.0.25.dist-info/METADATA
markdup-0.0.25.dist-info/WHEEL
markdup-0.0.25.dist-info/entry_points.txt
markdup-0.0.25.dist-info/top_level.txt
markdup-0.0.25.dist-info/RECORD
